psycopg2_connect/__init__.py
psycopg2_connect-0.0.2.dist-info/METADATA
psycopg2_connect-0.0.2.dist-info/WHEEL
psycopg2_connect-0.0.2.dist-info/top_level.txt
psycopg2_connect-0.0.2.dist-info/RECORD
